<?xml version="1.0" encoding="UTF-8"?>
<metadata xml:lang="en"><Esri><CreaDate>20220321</CreaDate><CreaTime>18474100</CreaTime><ArcGISFormat>1.0</ArcGISFormat><SyncOnce>TRUE</SyncOnce><DataProperties><itemProps><itemLocation><linkage Sync="TRUE">file://\\PRI-FS1\SWSGWmodeling\ISWS\Groundwater flow models\McHenry\old McH model\MH120320tBL-NWT\G572modelfiles\pumping_wells</linkage><protocol Sync="TRUE">Local Area Network</protocol></itemLocation></itemProps><copyHistory><copy source="\\PRI-FS1\SWSGWmodeling\ISWS\Groundwater flow models\McHenry\old McH model\MH120320tBL-NWT\pumping_wells" dest="\\PRI-FS1\SWSGWmodeling\ISWS\Groundwater flow models\McHenry\old McH model\MH120320tBL-NWT\G572modelfiles\pumping_wells" date="20220321" time="18474100"></copy></copyHistory></DataProperties></Esri></metadata>
